VERSION.py
rcat.py
rcat-1.0.1.dist-info/METADATA
rcat-1.0.1.dist-info/WHEEL
rcat-1.0.1.dist-info/entry_points.txt
rcat-1.0.1.dist-info/top_level.txt
rcat-1.0.1.dist-info/RECORD
